viberbot_prox/__init__.py
viberbot_prox/api/__init__.py
viberbot_prox/api/api.py
viberbot_prox/api/api_request_sender.py
viberbot_prox/api/bot_configuration.py
viberbot_prox/api/consts.py
viberbot_prox/api/event_type.py
viberbot_prox/api/message_sender.py
viberbot_prox/api/messages/__init__.py
viberbot_prox/api/messages/contact_message.py
viberbot_prox/api/messages/data_types/__init__.py
viberbot_prox/api/messages/data_types/contact.py
viberbot_prox/api/messages/data_types/location.py
viberbot_prox/api/messages/file_message.py
viberbot_prox/api/messages/keyboard_message.py
viberbot_prox/api/messages/location_message.py
viberbot_prox/api/messages/message.py
viberbot_prox/api/messages/message_type.py
viberbot_prox/api/messages/picture_message.py
viberbot_prox/api/messages/rich_media_message.py
viberbot_prox/api/messages/sticker_message.py
viberbot_prox/api/messages/text_message.py
viberbot_prox/api/messages/typed_message.py
viberbot_prox/api/messages/url_message.py
viberbot_prox/api/messages/video_message.py
viberbot_prox/api/user_profile.py
viberbot_prox/api/viber_requests/__init__.py
viberbot_prox/api/viber_requests/viber_conversation_started_request.py
viberbot_prox/api/viber_requests/viber_delivered_request.py
viberbot_prox/api/viber_requests/viber_failed_request.py
viberbot_prox/api/viber_requests/viber_message_request.py
viberbot_prox/api/viber_requests/viber_request.py
viberbot_prox/api/viber_requests/viber_seen_request.py
viberbot_prox/api/viber_requests/viber_subscribed_request.py
viberbot_prox/api/viber_requests/viber_unsubscribed_request.py
viberbot_prox/version.py
viberbot_prox-1.0.12.dist-info/LICENSE.md
viberbot_prox-1.0.12.dist-info/METADATA
viberbot_prox-1.0.12.dist-info/WHEEL
viberbot_prox-1.0.12.dist-info/RECORD
