Metadata-Version: 2.1
Name: viberbot_prox
Version: 1.0.12
Summary: forked from https://pypi.org/project/viberbot/ (https://github.com/Viber/viber-bot-python)
Home-page: https://github.com/rdnve/viberbot-proxy
License: MIT
Author: serje ù
Author-email: pleaseanswermeserjeu@icloud.com
Requires-Python: >=3.12,<3.13
Classifier: Development Status :: 3 - Alpha
Classifier: License :: OSI Approved :: MIT License
Classifier: Programming Language :: Python :: 3
Classifier: Programming Language :: Python :: 3.12
Requires-Dist: requests[socks] (>=2.32,<2.33)
Project-URL: Repository, https://github.com/rdnve/viberbot-proxy
